{
  "pets": [{"id":0,"name":"February","age":3,"type":"horse","description":"nice pet","hadOwner":false,"color":"green","statuses":[{"status":"fun","interval":2541,"diff":5},{"status":"feed","interval":566,"diff":6},{"status":"sleep","interval":3858,"diff":6},{"status":"toilet","interval":1090,"diff":1},{"status":"attention","interval":2045,"diff":7}]},{"id":1,"name":"May","age":12,"type":"butterfly","description":"nice pet","hadOwner":false,"color":"violet","statuses":[{"status":"fun","interval":1463,"diff":4},{"status":"feed","interval":1674,"diff":1},{"status":"sleep","interval":5661,"diff":6},{"status":"toilet","interval":1839,"diff":2},{"status":"attention","interval":641,"diff":9}]},{"id":2,"name":"January","age":17,"type":"goose","description":"nice pet","hadOwner":false,"color":"purple","statuses":[{"status":"fun","interval":2175,"diff":5},{"status":"feed","interval":658,"diff":10},{"status":"sleep","interval":6531,"diff":3},{"status":"toilet","interval":1423,"diff":3},{"status":"attention","interval":1292,"diff":9}]},{"id":3,"name":"Morning","age":12,"type":"horse","description":"nice pet","hadOwner":false,"color":"red","statuses":[{"status":"fun","interval":4366,"diff":1},{"status":"feed","interval":1710,"diff":12},{"status":"sleep","interval":6913,"diff":8},{"status":"toilet","interval":2931,"diff":2},{"status":"attention","interval":1849,"diff":5}]},{"id":4,"name":"March","age":13,"type":"chicken","description":"nice pet","hadOwner":false,"color":"yellow","statuses":[{"status":"fun","interval":2596,"diff":3},{"status":"feed","interval":1695,"diff":4},{"status":"sleep","interval":2884,"diff":5},{"status":"toilet","interval":2956,"diff":3},{"status":"attention","interval":2018,"diff":7}]},{"id":5,"name":"Thursday","age":3,"type":"cat","description":"nice pet","hadOwner":false,"color":"blue","statuses":[{"status":"fun","interval":3423,"diff":8},{"status":"feed","interval":585,"diff":13},{"status":"sleep","interval":3523,"diff":1},{"status":"toilet","interval":2249,"diff":1},{"status":"attention","interval":1935,"diff":5}]},{"id":6,"name":"February","age":17,"type":"butterfly","description":"nice pet","hadOwner":false,"color":"yellow","statuses":[{"status":"fun","interval":4588,"diff":3},{"status":"feed","interval":977,"diff":8},{"status":"sleep","interval":4516,"diff":7},{"status":"toilet","interval":1265,"diff":1},{"status":"attention","interval":543,"diff":7}]},{"id":7,"name":"Thursday","age":10,"type":"cat","description":"nice pet","hadOwner":false,"color":"orange","statuses":[{"status":"fun","interval":2896,"diff":7},{"status":"feed","interval":1160,"diff":8},{"status":"sleep","interval":4688,"diff":3},{"status":"toilet","interval":2019,"diff":1},{"status":"attention","interval":1797,"diff":2}]},{"id":8,"name":"September","age":1,"type":"chicken","description":"nice pet","hadOwner":false,"color":"violet","statuses":[{"status":"fun","interval":4258,"diff":9},{"status":"feed","interval":1437,"diff":9},{"status":"sleep","interval":2978,"diff":7},{"status":"toilet","interval":1038,"diff":1},{"status":"attention","interval":1497,"diff":4}]},{"id":9,"name":"December","age":9,"type":"butterfly","description":"nice pet","hadOwner":false,"color":"red","statuses":[{"status":"fun","interval":4921,"diff":1},{"status":"feed","interval":1130,"diff":14},{"status":"sleep","interval":6533,"diff":4},{"status":"toilet","interval":2404,"diff":4},{"status":"attention","interval":1894,"diff":8}]}]
}